./.gitignore
./.python-version
./PKG-INFO
./README.md
./main.py
./pyproject.toml
./uv.lock
./.vscode/settings.json
./code_executer/.gitignore
./code_executer/Dockerfile
./code_executer/executer.py
code_executer/.gitignore
code_executer/Dockerfile
code_executer/executer.py
containerizedcodeexecutermcp-0.1.0.dist-info/METADATA
containerizedcodeexecutermcp-0.1.0.dist-info/WHEEL
containerizedcodeexecutermcp-0.1.0.dist-info/entry_points.txt
containerizedcodeexecutermcp-0.1.0.dist-info/RECORD
