Metadata-Version: 2.4
Name: containerizedcodeexecutermcp
Version: 0.1.0
Summary: An MCP server that executes Python code in containerized environments.
Author: Efe Caliskan
Requires-Python: >=3.11
Requires-Dist: docker>=7.1.0
Requires-Dist: fastmcp>=2.10.6
Requires-Dist: httpx>=0.28.1
Requires-Dist: mcp[cli]>=1.12.2
